pylleida/__init__.py
pylleida/configuration.py
pylleida/api/__init__.py
pylleida/api/mail_cert.py
pylleida/templates/download_pdf.xml
pylleida/templates/get_default_settings.xml
pylleida/templates/list_pdf.xml
pylleida-0.4.0.dist-info/AUTHORS.rst
pylleida-0.4.0.dist-info/LICENSE
pylleida-0.4.0.dist-info/METADATA
pylleida-0.4.0.dist-info/WHEEL
pylleida-0.4.0.dist-info/top_level.txt
pylleida-0.4.0.dist-info/RECORD
