Metadata-Version: 2.1
Name: pylleida
Version: 0.4.0
Summary: A HTTP Python client to use the Lleida.net API
Home-page: https://github.com/reclamador/pylleida
Author: Nick M. Jaremek
Author-email: nick13jaremek@gmail.com
License: MIT license
Keywords: pylleida
Platform: UNKNOWN
Classifier: Natural Language :: English
Classifier: Programming Language :: Python :: 2
Classifier: Programming Language :: Python :: 2.7
Classifier: Programming Language :: Python :: 3
Classifier: Programming Language :: Python :: 3.5
Requires-Dist: Jinja2 (==2.9.5)
Requires-Dist: xmltodict (==0.10.2)
Requires-Dist: requests (==2.18.4)
